{
  "age_young": 18,
  "age_kid": 13,
  "max_financial_support": 85,
  "birth": "birthdate",
  "participant": "participant",
  "organizer": "organizercategory",
  "main_signup_only": {
    "pages": [
      "activity",
      "food",
      "wear"
    ],
    "items": {
      "extra": [
        "misc:party1"
      ]
    }
  },
  "errors": {
    "required": {
      "en": "This input may not be empty",
      "da": "Feltet må ikke være tomt"
    },
    "disabled": {
      "en": "Has been disabled",
      "da": "Skal ikke bruges"
    },
    "excludes": {
      "en": "May not be selected at the same time",
      "da": "Må ikke vælges samtidig"
    },
    "no_match": {
      "en": "No matching categories",
      "da": "Ingen kategorier der passer"
    },
    "not_on_list": {
      "en": "The content of this field is not on the list of allowed options.\n(Make sure to check the spelling and select a valid option from the list as you type)",
      "da": "Indholdet af feltet er ikke på listen over gyldige muligheder.\n(Kontroller stavning og vælg en værdi fra listen der dukker op mens du skriver)"
    },
    "require_one": {
      "en": "You must choose atleast one of the options",
      "da": "Du skal vælge mindst en af mulighederne"
    },
    "one_day": {
      "en": "You must choose atleast one day to attend Fastaval",
      "da": "Du skal vælge mindst en dag du kommer på Fastaval"
    },
    "sleeping_too_young": {
      "en": " years is too young to be allowed to sleep at Fastaval",
      "da": " år er for ung til at måtte overnatte på Fastaval"
    },
    "wine_too_young": {
      "en": " years is too young to be allowed to buy wine",
      "da": " år er for ung til at måtte købe vin"
    }
  },
  "input_error": {
    "en": "There some issues with the input on the current page.\nDo you want to stay and fix them?",
    "da": "Der er nogle problemer med indtastningen på den nuværende side.\nVil du blive på siden og rette dem?"
  },
  "sub_total": {
    "en": "Sub total",
    "da": "Sub total"
  },
  "pieces": {
    "en": "pcs.",
    "da": "stk."
  },
  "dkk": {
    "en": "DKK",
    "da": "kr."
  }
}